Metadata-Version: 2.1
Name: predictionscorer
Version: 1.0.1
Summary: Python library to score predictions
Home-page: https://github.com/yhoiseth/python-prediction-scorer
Author: Yngve Hoiseth
Author-email: yngve@hoiseth.net
License: MIT
Platform: UNKNOWN
Requires-Python: >=3.8,<3.9
